SparkStream/VERSION
SparkStream/__init__.py
SparkStream/streamer.py
SparkStream/utils.py
SparkStream/Config/__init__.py
SparkStream/Config/logging_config.py
SparkStream/Text/__init__.py
SparkStream/Text/text_analyzer.py
SparkStream/Text/text_cleaner.py
SparkStream-1.2.1.dist-info/LICENSE
SparkStream-1.2.1.dist-info/METADATA
SparkStream-1.2.1.dist-info/WHEEL
SparkStream-1.2.1.dist-info/top_level.txt
SparkStream-1.2.1.dist-info/RECORD
