Metadata-Version: 2.1
Name: SparkStream
Version: 1.2.1
Summary: A simple spark streaming handler.
Home-page: https://github.com/HassanRady/SparkStream
Author: Hassan Rady
Author-email: hassan.khaled.rady@gmail.com
License: MIT license
Keywords: Tweets
Classifier: Development Status :: 2 - Pre-Alpha
Classifier: Intended Audience :: Developers
Classifier: License :: OSI Approved :: MIT License
Classifier: Natural Language :: English
Classifier: Programming Language :: Python :: 3
Classifier: Programming Language :: Python :: 3.6
Classifier: Programming Language :: Python :: 3.7
Classifier: Programming Language :: Python :: 3.8
Requires-Python: >=3.6.0
License-File: LICENSE
Requires-Dist: uvicorn (==0.17.6)
Requires-Dist: fastapi (==0.78.0)
Requires-Dist: python-dotenv
